topa/__init__.py
topa-1.0.1.dist-info/LICENSE
topa-1.0.1.dist-info/METADATA
topa-1.0.1.dist-info/WHEEL
topa-1.0.1.dist-info/entry_points.txt
topa-1.0.1.dist-info/top_level.txt
topa-1.0.1.dist-info/RECORD
