Metadata-Version: 2.1
Name: topa
Version: 1.0.1
Summary: A Top Output Python Analyzer
Home-page: https://github.com/jwenjian/topa
Author: JIANG Wenjian
Author-email: wenjian.jiang@foxmail.com
License: GPL-3.0
Platform: UNKNOWN
Requires-Dist: click
